{
  "instance_code": "DEU",
  "instance_name": "Germany",
  "locale": "de",
  "hostnames": {
    "app": "deu-app.dive25.com",
    "api": "deu-api.dive25.com",
    "idp": "deu-idp.dive25.com",
    "kas": "deu-kas.dive25.com"
  },
  "ports": {
    "frontend": 3002,
    "backend": 4002,
    "keycloak_http": 8083,
    "keycloak_https": 8445,
    "mongodb": 27019,
    "redis": 6381,
    "opa": 8183,
    "kas": 8092,
    "postgres": 5435,
    "cloudflared_metrics": 9128
  },
  "theme": {
    "primary_color": "#000000",
    "secondary_color": "#DD0000",
    "accent_color": "#FFCC00",
    "background_image": "background-deu.jpg",
    "keycloak_theme": "dive-v3-deu",
    "css_variables": {
      "--instance-primary": "#000000",
      "--instance-secondary": "#DD0000",
      "--instance-accent": "#FFCC00",
      "--instance-text": "#ffffff",
      "--instance-banner-bg": "linear-gradient(135deg, #000000 0%, #DD0000 50%, #FFCC00 100%)"
    }
  },
  "federation_partners": ["USA", "FRA", "GBR"],
  "cloudflare": {
    "tunnel_id": "a1b2c3d4-e5f6-7890-abcd-ef1234567890",
    "tunnel_name": "dive-v3-deu-tunnel"
  },
  "test_users": {
    "prefix": "testuser-deu",
    "password": "DiveDemo2025!",
    "count": 4
  }
}








